MessageQueueService/__init__.py
MessageQueueService/__main__.py
MessageQueueService/const.py
MessageQueueService/service.py
pih_msg_q-1.1.dist-info/METADATA
pih_msg_q-1.1.dist-info/WHEEL
pih_msg_q-1.1.dist-info/entry_points.txt
pih_msg_q-1.1.dist-info/top_level.txt
pih_msg_q-1.1.dist-info/RECORD
