Metadata-Version: 2.1
Name: pih-msg-q
Version: 1.1
Summary: PIH Message queue service module
Home-page: https://pacifichosp.com/
Author: Nikita Karachentsev
Author-email: it@pacifichosp.com
License: MIT
Requires-Dist: ipih
